setup.py
ssdb.py
ssdb.py.egg-info/PKG-INFO
ssdb.py.egg-info/SOURCES.txt
ssdb.py.egg-info/dependency_links.txt
ssdb.py.egg-info/requires.txt
ssdb.py.egg-info/top_level.txt