Metadata-Version: 1.1
Name: ssdb.py
Version: 0.1.7
Summary: Ssdb Python Client Library
Home-page: https://github.com/hit9/ssdb.py
Author: hit9
Author-email: nz2324@126.com
License: bsd2
Keywords: ssdb,client,library
Platform: UNKNOWN
Classifier: Development Status :: 3 - Alpha
Classifier: Intended Audience :: Developers
Classifier: License :: OSI Approved :: BSD License
Classifier: Operating System :: OS Independent
Classifier: Programming Language :: Python :: 2.7
Classifier: Programming Language :: Python :: 3.3
Classifier: Programming Language :: Python :: 3.4
Classifier: Programming Language :: Python :: Implementation :: CPython
Classifier: Programming Language :: Python :: Implementation :: PyPy
Classifier: Topic :: Software Development :: Libraries :: Python Modules
